Metadata-Version: 2.1
Name: tqsdk-zq-otg-ctp
Version: 1.1.2
Summary: TianQin SDK - zq_otg_ctp lib
Home-page: https://www.shinnytech.com/tqsdk
Author: TianQin
Author-email: tianqincn@gmail.com
License: UNKNOWN
Platform: UNKNOWN
Requires-Python: >=3
Requires-Dist: tqsdk (==3.7.2)
Requires-Dist: tqsdk-zq-otg (==1.1.2)
